ninjaclient/__init__.py
ninjaclient/ninja_client.py
ninjaclient-0.1.3.dist-info/LICENSE
ninjaclient-0.1.3.dist-info/METADATA
ninjaclient-0.1.3.dist-info/WHEEL
ninjaclient-0.1.3.dist-info/RECORD
