Metadata-Version: 2.1
Name: ninjaclient
Version: 0.1.3
Summary: A client for querying data from the Renewables Ninja API.
Home-page: https://ninjaclient.readthedocs.io/en/latest/
License: MIT
Author: Martin Hjelmeland
Author-email: marhje90@gmail.com
Requires-Python: >=3.10,<4.0
Classifier: License :: OSI Approved :: MIT License
Classifier: Programming Language :: Python :: 3
Classifier: Programming Language :: Python :: 3.10
Classifier: Programming Language :: Python :: 3.11
Classifier: Programming Language :: Python :: 3.12
Requires-Dist: pandas (>=2.2.0,<3.0.0)
Requires-Dist: requests (>=2.31.0,<3.0.0)
Project-URL: Repository, https://github.com/martinhjel/ninjaclient
